alabester-4.2.0.dist-info/DESCRIPTION.rst
alabester-4.2.0.dist-info/entry_points.txt
alabester-4.2.0.dist-info/RECORD
alabester-4.2.0.dist-info/METADATA
alabester-4.2.0.dist-info/top_level.txt
alabester-4.2.0.dist-info/WHEEL
alabester-4.2.0.dist-info/metadata.json
alabester-4.2.0.dist-info/LICENSE.txt
alabester/__init__.py
alabester/support.py
alabester/_version.py
alabester/relations.html
alabester/layout.html
alabester/theme.conf
alabester/about.html
alabester/donate.html
alabester/navigation.html
alabester/static/alabester.css_t
alabester/static/custom.css
