Metadata-Version: 2.0
Name: alabester
Version: 4.2.0
Summary: A non-configurable sidebar-enabled Sphinx theme borked from Alabaster
Home-page: https://github.com/introt/alabester
Author: introt
Author-email: introt@koti.fimnet.fi
License: UNKNOWN
Platform: UNKNOWN
Classifier: Development Status :: 7 - Inactive
Classifier: Intended Audience :: Developers
Classifier: License :: OSI Approved :: BSD License
Classifier: Operating System :: OS Independent
Classifier: Programming Language :: Python
Classifier: Programming Language :: Python :: 3.7
Classifier: Programming Language :: Python :: Implementation :: CPython
Classifier: Programming Language :: Python :: Implementation :: PyPy
Classifier: Topic :: Documentation
Classifier: Topic :: Software Development :: Documentation
